terick
