Metadata-Version: 2.1
Name: terick
Version: 0.2.6
Summary: Package full of simple functions
Author: HaxoTF
Author-email: <haxotf@gmail.com>
Keywords: python,regular,helper
Classifier: Development Status :: 5 - Production/Stable
Classifier: Intended Audience :: Developers
Classifier: Programming Language :: Python
Classifier: Operating System :: MacOS :: MacOS X
Classifier: Operating System :: Microsoft :: Windows
Classifier: Natural Language :: English
